<?xml version="1.0"?>
<psalm
    phpVersion="8.2"
    errorLevel="8"
    findUnusedPsalmSuppress="true"
    findUnusedCode="false"
    findUnusedBaselineEntry="false"
    resolveFromConfigFile="true"
    allowStringToStandInForClass="true"
    cacheDirectory="/tmp/psalm"
    xmlns:xsi="http://www.w3.org/2001/XMLSchema-instance"
    xmlns="https://getpsalm.org/schema/config"
    xsi:schemaLocation="https://getpsalm.org/schema/config vendor/vimeo/psalm/config.xsd"
>
    <projectFiles>
        <directory name="src" />
        <ignoreFiles>
            <directory name="vendor" />
        </ignoreFiles>
    </projectFiles>
    <issueHandlers>
        <InvalidClassConstantType errorLevel="suppress" />
        <PropertyNotSetInConstructor errorLevel="suppress" />
        <TooManyTemplateParams errorLevel="suppress" />
        <NoInterfaceProperties errorLevel="suppress" />
        <RedundantCastGivenDocblockType errorLevel="suppress" />
        <TypeDoesNotContainType errorLevel="suppress" />
        <RedundantPropertyInitializationCheck errorLevel="suppress" />
        <RedundantCondition errorLevel="suppress" />
        <UnresolvableInclude errorLevel="suppress" />
        <RedundantConditionGivenDocblockType errorLevel="suppress" />
        <DeprecatedMethod errorLevel="suppress" />
    </issueHandlers>
</psalm>
